jieba_calcu/__init__.py
jieba_calcu/mywrapper.py
jieba_calcu/viterbi.py
jieba_calcu/word_discovery.py
test-data/__init__.py
test-data/append_helper.py
test-data/http_inf.py
test-data/req.py
test-data/test.py
test-data/test_flask.py
test-data/test_ner.py
jieba_calcu-1.0.7.dist-info/LICENSE
jieba_calcu-1.0.7.dist-info/METADATA
jieba_calcu-1.0.7.dist-info/WHEEL
jieba_calcu-1.0.7.dist-info/entry_points.txt
jieba_calcu-1.0.7.dist-info/top_level.txt
jieba_calcu-1.0.7.dist-info/RECORD
