Metadata-Version: 1.0
Name: jieba-calcu
Version: 1.0.7
Summary: word discovery
Home-page: UNKNOWN
Author: QinHaiNing
Author-email: qinhaining@ultrapower.com.cn
License: UNKNOWN
Keywords: command,line,tool
Platform: UNKNOWN
